lazyscribe_joblib/__init__.py
lazyscribe_joblib/_meta.py
lazyscribe_joblib-0.1.1.dist-info/WHEEL
lazyscribe_joblib-0.1.1.dist-info/entry_points.txt
lazyscribe_joblib-0.1.1.dist-info/METADATA
lazyscribe_joblib-0.1.1.dist-info/RECORD
